nta_build_tools-0.5.0.dist-info/METADATA
nta_build_tools-0.5.0.dist-info/RECORD
nta_build_tools-0.5.0.dist-info/WHEEL
nta_build_tools-0.5.0.dist-info/entry_points.txt
nta_build_tools-0.5.0.dist-info/top_level.txt
ntabuildtools/__init__.py
ntabuildtools/build.py
ntabuildtools/clean.py
ntabuildtools/install.py
ntabuildtools/repos.py
ntabuildtools/update.py
ntabuildtools/utils.py
