Metadata-Version: 2.1
Name: nta-build-tools
Version: 0.5.0
Summary: Build tools for Numenta developers
Home-page: https://github.com/numentacorp/nta-build-tools
Author: Numenta
Author-email: UNKNOWN
License: UNKNOWN
Platform: UNKNOWN
